Workbook

Sheet Project Instructions
A1: PR. 2 Analyzer
A2: Topics: - Conditional Formatting - WHAT IF Analysis - Linear Regression (Using Data Analysis Toolpak) - Data Analysis Feature (Descriptive Stats, Regression, Histogram) - Data Storytelling - Add Symbols or Arrows in Custom Formatting - Create Timestamp - Find High-Value Customers using Groupby(), index(), and match() combination - Advanced Descriptive Analytics - Pivot Table with Dashboard - Creating bar charts - Creating line charts - Creating pie charts Main Tasks: 1. Apply conditional formatting to highlight top 10 customers based on total purchase. 2. Perform WHAT IF Analysis to see impact of changing discount on total profit. 3. Use Data Analysis Toolpak to run Linear Regression (Profit vs Sales). 4. Use 'Descriptive Statistics' from Analysis Toolpak on the dataset. 5. Add up/down arrows on monthly sales growth. 6. Create a timestamp column using NOW(). 7. Identify high-value customers using index(), match(), and filters. 8. Create Pivot Table to analyze total sales by region and product. 9. Create bar, line, and pie charts to visualize KPIs. 10. Summarize insights using a dashboard. Deliverable: Complete the given worksheet by applying the required formulas in respective sheets.

Sheet Dataset
A1: Customer_ID | B1: Customer_Name | C1: Region | D1: Product_Category | E1: Sales | F1: Quantity | G1: Discount | H1: Order_Date | I1: Profit | J1: Customer_Total_Sales | K1: Customer_Rank | L1: Report_Timestamp
A2: CUST019 | B2: James Davis | C2: West | D2: Books | E2: 1036.09 | F2: 4 | G2: 0.2 | H2: 45392 | I2: 331.55 | J2: =SUMIF($A$2:$A$201,A2,$E$2:$E$201) -> 4640.11 | K2: =RANK(J2,$J$2:$J$201) -> 159 | L2: =NOW() -> 46280.699
A3: CUST012 | B3: Robert Anderson | C3: West | D3: Clothing | E3: 1101.28 | F3: 3 | G3: 0.2 | H3: 45393 | I3: 440.51 | J3: =SUMIF($A$2:$A$201,A3,$E$2:$E$201) -> 8339 | K3: =RANK(J3,$J$2:$J$201) -> 70 | L3: =NOW() -> 46280.699
A4: CUST017 | B4: James Taylor | C4: East | D4: Books | E4: 713.34 | F4: 17 | G4: 0 | H4: 45396 | I4: 285.34 | J4: =SUMIF($A$2:$A$201,A4,$E$2:$E$201) -> 3419.2 | K4: =RANK(J4,$J$2:$J$201) -> 191 | L4: =NOW() -> 46280.699
A5: CUST005 | B5: Robert Anderson | C5: South | D5: Electronics | E5: 760.93 | F5: 4 | G5: 0.15 | H5: 45396 | I5: 161.7 | J5: =SUMIF($A$2:$A$201,A5,$E$2:$E$201) -> 6666.13 | K5: =RANK(J5,$J$2:$J$201) -> 114 | L5: =NOW() -> 46280.699
A6: CUST030 | B6: James Wilson | C6: North | D6: Books | E6: 847 | F6: 12 | G6: 0.2 | H6: 45397 | I6: 271.04 | J6: =SUMIF($A$2:$A$201,A6,$E$2:$E$201) -> 7928.71 | K6: =RANK(J6,$J$2:$J$201) -> 79 | L6: =NOW() -> 46280.699
A7: CUST007 | B7: Michael Anderson | C7: North | D7: Furniture | E7: 965.64 | F7: 8 | G7: 0.1 | H7: 45398 | I7: 304.18 | J7: =SUMIF($A$2:$A$201,A7,$E$2:$E$201) -> 9941.88 | K7: =RANK(J7,$J$2:$J$201) -> 24 | L7: =NOW() -> 46280.699
A8: CUST001 | B8: Linda Wilson | C8: West | D8: Electronics | E8: 1317.53 | F8: 12 | G8: 0.05 | H8: 45398 | I8: 312.91 | J8: =SUMIF($A$2:$A$201,A8,$E$2:$E$201) -> 6549.55 | K8: =RANK(J8,$J$2:$J$201) -> 120 | L8: =NOW() -> 46280.699
A9: CUST026 | B9: Mary Davis | C9: East | D9: Furniture | E9: 1074.47 | F9: 6 | G9: 0.2 | H9: 45401 | I9: 300.85 | J9: =SUMIF($A$2:$A$201,A9,$E$2:$E$201) -> 9371.81 | K9: =RANK(J9,$J$2:$J$201) -> 44 | L9: =NOW() -> 46280.699
A10: CUST009 | B10: Linda Jackson | C10: Central | D10: Books | E10: 501.54 | F10: 11 | G10: 0.05 | H10: 45401 | I10: 190.59 | J10: =SUMIF($A$2:$A$201,A10,$E$2:$E$201) -> 6505.2 | K10: =RANK(J10,$J$2:$J$201) -> 127 | L10: =NOW() -> 46280.699
A11: CUST010 | B11: David Thomas | C11: Central | D11: Clothing | E11: 737.31 | F11: 2 | G11: 0.05 | H11: 45401 | I11: 350.22 | J11: =SUMIF($A$2:$A$201,A11,$E$2:$E$201) -> 4259.22 | K11: =RANK(J11,$J$2:$J$201) -> 173 | L11: =NOW() -> 46280.699
A12: CUST014 | B12: Emma Davis | C12: West | D12: Office Supplies | E12: 1572.82 | F12: 6 | G12: 0.05 | H12: 45402 | I12: 672.38 | J12: =SUMIF($A$2:$A$201,A12,$E$2:$E$201) -> 6729.89 | K12: =RANK(J12,$J$2:$J$201) -> 102 | L12: =NOW() -> 46280.699
A13: CUST014 | B13: David Thomas | C13: Central | D13: Books | E13: 1343.13 | F13: 14 | G13: 0.15 | H13: 45404 | I13: 456.66 | J13: =SUMIF($A$2:$A$201,A13,$E$2:$E$201) -> 6729.89 | K13: =RANK(J13,$J$2:$J$201) -> 102 | L13: =NOW() -> 46280.699
... A201: CUST016 | B201: David Thomas | C201: South | D201: Clothing | E201: 928.32 | F201: 2 | G201: 0.05 | H201: 45754 | I201: 440.95 | J201: =SUMIF($A$2:$A$201,A201,$E$2:$E$201) -> 3369.17 | K201: =RANK(J201,$J$2:$J$201) -> 195 | L201: =NOW() -> 46280.699

Sheet Dashboard
A1: Sales Performance Dashboard
A2: Auto-generated KPIs, charts and data storytelling insights -- all formulas, updates live with the Dataset.
A4: Total Sales | B4: Total Profit | C4: Total Orders | D4: Unique Customers | E4: Avg Discount | F4: Overall Margin
A5: =SUM(Dataset!$E$2:$E$201) -> 195217.76 | B5: =SUM(Dataset!$I$2:$I$201) -> 68287.01 | C5: =COUNTA(Dataset!$A$2:$A$201) -> 200 | D5: =SUMPRODUCT(1/COUNTIF(Dataset!$A$2:$A$201,Dataset!$A$2:$A$201)) -> 30 | E5: =AVERAGE(Dataset!$G$2:$G$201) -> 0.09725 | F5: =SUM(Dataset!$I$2:$I$201)/SUM(Dataset!$E$2:$E$201) -> 0.34979917 | I5: Rank | J5: Customer_ID | K5: Customer_Name | L5: Total_Sales
I6: ='High-Value Customers'!A39 -> 1 | J6: Top 10 Customers by Total Sales | K6: ='High-Value Customers'!C39 -> Linda Taylor | L6: ='High-Value Customers'!D39 -> 11611.06
I7: ='High-Value Customers'!A40 -> 2 | J7: ='High-Value Customers'!B40 -> CUST028 | K7: ='High-Value Customers'!C40 -> Linda Taylor | L7: ='High-Value Customers'!D40 -> 10293.87
I8: ='High-Value Customers'!A41 -> 3 | J8: ='High-Value Customers'!B41 -> CUST007 | K8: ='High-Value Customers'!C41 -> Michael Anderson | L8: ='High-Value Customers'!D41 -> 9941.88
I9: ='High-Value Customers'!A42 -> 4 | J9: ='High-Value Customers'!B42 -> CUST008 | K9: ='High-Value Customers'!C42 -> Robert Anderson | L9: ='High-Value Customers'!D42 -> 9760.8
I10: ='High-Value Customers'!A43 -> 5 | J10: ='High-Value Customers'!B43 -> CUST026 | K10: ='High-Value Customers'!C43 -> Mary Davis | L10: ='High-Value Customers'!D43 -> 9371.81
I11: ='High-Value Customers'!A44 -> 6 | J11: ='High-Value Customers'!B44 -> CUST021 | K11: ='High-Value Customers'!C44 -> Sarah Anderson | L11: ='High-Value Customers'!D44 -> 8740.18
I12: ='High-Value Customers'!A45 -> 7 | J12: ='High-Value Customers'!B45 -> CUST003 | K12: ='High-Value Customers'!C45 -> Emma Davis | L12: ='High-Value Customers'!D45 -> 8490.18
I13: ='High-Value Customers'!A46 -> 8 | J13: ='High-Value Customers'!B46 -> CUST012 | K13: ='High-Value Customers'!C46 -> Robert Anderson | L13: ='High-Value Customers'!D46 -> 8339
I14: ='High-Value Customers'!A47 -> 9 | J14: ='High-Value Customers'!B47 -> CUST030 | K14: ='High-Value Customers'!C47 -> James Wilson | L14: ='High-Value Customers'!D47 -> 7928.71
I15: ='High-Value Customers'!A48 -> 10 | J15: ='High-Value Customers'!B48 -> CUST004 | K15: ='High-Value Customers'!C48 -> Lisa Thomas | L15: ='High-Value Customers'!D48 -> 7813.59

Sheet High-Value Customers
A1: High-Value Customer Identification (INDEX / MATCH / SUMIF)
A5: Customer_ID | B5: Customer_Name | C5: Total_Sales | D5: Total_Profit | E5: Order_Count | F5: Avg_Order_Value | G5: Sales_Rank | H5: Value_Segment
A6: ="CUST"&TEXT(ROW()-5,"000") -> CUST001 | B6: =IFERROR(INDEX(Dataset!$B$2:$B$201,MATCH(A6,Dataset!$A$2:$A$201,0)),"") -> Linda Wilson | C6: =SUMIF(Dataset!$A$2:$A$201,A6,Dataset!$E$2:$E$201) -> 6549.55 | D6: =SUMIF(Dataset!$A$2:$A$201,A6,Dataset!$I$2:$I$201) -> 1868.77 | E6: =COUNTIF(Dataset!$A$2:$A$201,A6) -> 7 | F6: =IFERROR(C6/E6,0) -> 935.65 | G6: =RANK(C6,$C$6:$C$35) -> 15 | H6: =IF(G6<=10,"High-Value","Standard") -> Standard
A7: ="CUST"&TEXT(ROW()-5,"000") -> CUST002 | B7: =IFERROR(INDEX(Dataset!$B$2:$B$201,MATCH(A7,Dataset!$A$2:$A$201,0)),"") -> Lisa Davis | C7: =SUMIF(Dataset!$A$2:$A$201,A7,Dataset!$E$2:$E$201) -> 6481.43 | D7: =SUMIF(Dataset!$A$2:$A$201,A7,Dataset!$I$2:$I$201) -> 2210.74 | E7: =COUNTIF(Dataset!$A$2:$A$201,A7) -> 6 | F7: =IFERROR(C7/E7,0) -> 1080.2383 | G7: =RANK(C7,$C$6:$C$35) -> 17 | H7: =IF(G7<=10,"High-Value","Standard") -> Standard
A8: ="CUST"&TEXT(ROW()-5,"000") -> CUST003 | B8: =IFERROR(INDEX(Dataset!$B$2:$B$201,MATCH(A8,Dataset!$A$2:$A$201,0)),"") -> Emma Davis | C8: =SUMIF(Dataset!$A$2:$A$201,A8,Dataset!$E$2:$E$201) -> 8490.18 | D8: =SUMIF(Dataset!$A$2:$A$201,A8,Dataset!$I$2:$I$201) -> 2652.75 | E8: =COUNTIF(Dataset!$A$2:$A$201,A8) -> 9 | F8: =IFERROR(C8/E8,0) -> 943.35333 | G8: =RANK(C8,$C$6:$C$35) -> 7 | H8: =IF(G8<=10,"High-Value","Standard") -> High-Value
A9: ="CUST"&TEXT(ROW()-5,"000") -> CUST004 | B9: =IFERROR(INDEX(Dataset!$B$2:$B$201,MATCH(A9,Dataset!$A$2:$A$201,0)),"") -> Lisa Thomas | C9: =SUMIF(Dataset!$A$2:$A$201,A9,Dataset!$E$2:$E$201) -> 7813.59 | D9: =SUMIF(Dataset!$A$2:$A$201,A9,Dataset!$I$2:$I$201) -> 3211.82 | E9: =COUNTIF(Dataset!$A$2:$A$201,A9) -> 7 | F9: =IFERROR(C9/E9,0) -> 1116.2271 | G9: =RANK(C9,$C$6:$C$35) -> 10 | H9: =IF(G9<=10,"High-Value","Standard") -> High-Value
A10: ="CUST"&TEXT(ROW()-5,"000") -> CUST005 | B10: =IFERROR(INDEX(Dataset!$B$2:$B$201,MATCH(A10,Dataset!$A$2:$A$201,0)),"") -> Robert Anderson | C10: =SUMIF(Dataset!$A$2:$A$201,A10,Dataset!$E$2:$E$201) -> 6666.13 | D10: =SUMIF(Dataset!$A$2:$A$201,A10,Dataset!$I$2:$I$201) -> 1982.39 | E10: =COUNTIF(Dataset!$A$2:$A$201,A10) -> 6 | F10: =IFERROR(C10/E10,0) -> 1111.0217 | G10: =RANK(C10,$C$6:$C$35) -> 14 | H10: =IF(G10<=10,"High-Value","Standard") -> Standard
A11: ="CUST"&TEXT(ROW()-5,"000") -> CUST006 | B11: =IFERROR(INDEX(Dataset!$B$2:$B$201,MATCH(A11,Dataset!$A$2:$A$201,0)),"") -> Mary Jackson | C11: =SUMIF(Dataset!$A$2:$A$201,A11,Dataset!$E$2:$E$201) -> 2699.75 | D11: =SUMIF(Dataset!$A$2:$A$201,A11,Dataset!$I$2:$I$201) -> 837.06 | E11: =COUNTIF(Dataset!$A$2:$A$201,A11) -> 2 | F11: =IFERROR(C11/E11,0) -> 1349.875 | G11: =RANK(C11,$C$6:$C$35) -> 30 | H11: =IF(G11<=10,"High-Value","Standard") -> Standard
A12: ="CUST"&TEXT(ROW()-5,"000") -> CUST007 | B12: =IFERROR(INDEX(Dataset!$B$2:$B$201,MATCH(A12,Dataset!$A$2:$A$201,0)),"") -> Michael Anderson | C12: =SUMIF(Dataset!$A$2:$A$201,A12,Dataset!$E$2:$E$201) -> 9941.88 | D12: =SUMIF(Dataset!$A$2:$A$201,A12,Dataset!$I$2:$I$201) -> 3936.26 | E12: =COUNTIF(Dataset!$A$2:$A$201,A12) -> 10 | F12: =IFERROR(C12/E12,0) -> 994.188 | G12: =RANK(C12,$C$6:$C$35) -> 3 | H12: =IF(G12<=10,"High-Value","Standard") -> High-Value
A13: ="CUST"&TEXT(ROW()-5,"000") -> CUST008 | B13: =IFERROR(INDEX(Dataset!$B$2:$B$201,MATCH(A13,Dataset!$A$2:$A$201,0)),"") -> Robert Anderson | C13: =SUMIF(Dataset!$A$2:$A$201,A13,Dataset!$E$2:$E$201) -> 9760.8 | D13: =SUMIF(Dataset!$A$2:$A$201,A13,Dataset!$I$2:$I$201) -> 3442.48 | E13: =COUNTIF(Dataset!$A$2:$A$201,A13) -> 10 | F13: =IFERROR(C13/E13,0) -> 976.08 | G13: =RANK(C13,$C$6:$C$35) -> 4 | H13: =IF(G13<=10,"High-Value","Standard") -> High-Value
A14: ="CUST"&TEXT(ROW()-5,"000") -> CUST009 | B14: =IFERROR(INDEX(Dataset!$B$2:$B$201,MATCH(A14,Dataset!$A$2:$A$201,0)),"") -> Linda Jackson | C14: =SUMIF(Dataset!$A$2:$A$201,A14,Dataset!$E$2:$E$201) -> 6505.2 | D14: =SUMIF(Dataset!$A$2:$A$201,A14,Dataset!$I$2:$I$201) -> 2052.54 | E14: =COUNTIF(Dataset!$A$2:$A$201,A14) -> 7 | F14: =IFERROR(C14/E14,0) -> 929.31429 | G14: =RANK(C14,$C$6:$C$35) -> 16 | H14: =IF(G14<=10,"High-Value","Standard") -> Standard
A15: ="CUST"&TEXT(ROW()-5,"000") -> CUST010 | B15: =IFERROR(INDEX(Dataset!$B$2:$B$201,MATCH(A15,Dataset!$A$2:$A$201,0)),"") -> David Thomas | C15: =SUMIF(Dataset!$A$2:$A$201,A15,Dataset!$E$2:$E$201) -> 4259.22 | D15: =SUMIF(Dataset!$A$2:$A$201,A15,Dataset!$I$2:$I$201) -> 1529.32 | E15: =COUNTIF(Dataset!$A$2:$A$201,A15) -> 5 | F15: =IFERROR(C15/E15,0) -> 851.844 | G15: =RANK(C15,$C$6:$C$35) -> 24 | H15: =IF(G15<=10,"High-Value","Standard") -> Standard
A16: ="CUST"&TEXT(ROW()-5,"000") -> CUST011 | B16: =IFERROR(INDEX(Dataset!$B$2:$B$201,MATCH(A16,Dataset!$A$2:$A$201,0)),"") -> Mary Davis | C16: =SUMIF(Dataset!$A$2:$A$201,A16,Dataset!$E$2:$E$201) -> 3762.29 | D16: =SUMIF(Dataset!$A$2:$A$201,A16,Dataset!$I$2:$I$201) -> 1545.04 | E16: =COUNTIF(Dataset!$A$2:$A$201,A16) -> 4 | F16: =IFERROR(C16/E16,0) -> 940.5725 | G16: =RANK(C16,$C$6:$C$35) -> 27 | H16: =IF(G16<=10,"High-Value","Standard") -> Standard
A17: ="CUST"&TEXT(ROW()-5,"000") -> CUST012 | B17: =IFERROR(INDEX(Dataset!$B$2:$B$201,MATCH(A17,Dataset!$A$2:$A$201,0)),"") -> Robert Anderson | C17: =SUMIF(Dataset!$A$2:$A$201,A17,Dataset!$E$2:$E$201) -> 8339 | D17: =SUMIF(Dataset!$A$2:$A$201,A17,Dataset!$I$2:$I$201) -> 2988.71 | E17: =COUNTIF(Dataset!$A$2:$A$201,A17) -> 9 | F17: =IFERROR(C17/E17,0) -> 926.55556 | G17: =RANK(C17,$C$6:$C$35) -> 8 | H17: =IF(G17<=10,"High-Value","Standard") -> High-Value
... A35: ="CUST"&TEXT(ROW()-5,"000") -> CUST030 | B35: =IFERROR(INDEX(Dataset!$B$2:$B$201,MATCH(A35,Dataset!$A$2:$A$201,0)),"") -> James Wilson | C35: =SUMIF(Dataset!$A$2:$A$201,A35,Dataset!$E$2:$E$201) -> 7928.71 | D35: =SUMIF(Dataset!$A$2:$A$201,A35,Dataset!$I$2:$I$201) -> 2965.48 | E35: =COUNTIF(Dataset!$A$2:$A$201,A35) -> 9 | F35: =IFERROR(C35/E35,0) -> 880.96778 | G35: =RANK(C35,$C$6:$C$35) -> 9 | H35: =IF(G35<=10,"High-Value","Standard") -> High-Value
A37: Top 10 Customers - Sorted by Total Sales (LARGE + INDEX/MATCH)
A38: Rank | B38: Customer_ID | C38: Customer_Name | D38: Total_Sales | E38: Total_Profit
A39: 1 | B39: =INDEX($A$6:$A$35,MATCH(D39,$C$6:$C$35,0)) -> CUST015 | C39: =INDEX($B$6:$B$35,MATCH(D39,$C$6:$C$35,0)) -> Linda Taylor | D39: =LARGE($C$6:$C$35,A39) -> 11611.06 | E39: =INDEX($D$6:$D$35,MATCH(D39,$C$6:$C$35,0)) -> 4201.59
A40: 2 | B40: =INDEX($A$6:$A$35,MATCH(D40,$C$6:$C$35,0)) -> CUST028 | C40: =INDEX($B$6:$B$35,MATCH(D40,$C$6:$C$35,0)) -> Linda Taylor | D40: =LARGE($C$6:$C$35,A40) -> 10293.87 | E40: =INDEX($D$6:$D$35,MATCH(D40,$C$6:$C$35,0)) -> 3541.02
A41: 3 | B41: =INDEX($A$6:$A$35,MATCH(D41,$C$6:$C$35,0)) -> CUST007 | C41: =INDEX($B$6:$B$35,MATCH(D41,$C$6:$C$35,0)) -> Michael Anderson | D41: =LARGE($C$6:$C$35,A41) -> 9941.88 | E41: =INDEX($D$6:$D$35,MATCH(D41,$C$6:$C$35,0)) -> 3936.26
A42: 4 | B42: =INDEX($A$6:$A$35,MATCH(D42,$C$6:$C$35,0)) -> CUST008 | C42: =INDEX($B$6:$B$35,MATCH(D42,$C$6:$C$35,0)) -> Robert Anderson | D42: =LARGE($C$6:$C$35,A42) -> 9760.8 | E42: =INDEX($D$6:$D$35,MATCH(D42,$C$6:$C$35,0)) -> 3442.48
A43: 5 | B43: =INDEX($A$6:$A$35,MATCH(D43,$C$6:$C$35,0)) -> CUST026 | C43: =INDEX($B$6:$B$35,MATCH(D43,$C$6:$C$35,0)) -> Mary Davis | D43: =LARGE($C$6:$C$35,A43) -> 9371.81 | E43: =INDEX($D$6:$D$35,MATCH(D43,$C$6:$C$35,0)) -> 2922.02
A44: 6 | B44: =INDEX($A$6:$A$35,MATCH(D44,$C$6:$C$35,0)) -> CUST021 | C44: =INDEX($B$6:$B$35,MATCH(D44,$C$6:$C$35,0)) -> Sarah Anderson | D44: =LARGE($C$6:$C$35,A44) -> 8740.18 | E44: =INDEX($D$6:$D$35,MATCH(D44,$C$6:$C$35,0)) -> 2848.62
A45: 7 | B45: =INDEX($A$6:$A$35,MATCH(D45,$C$6:$C$35,0)) -> CUST003 | C45: =INDEX($B$6:$B$35,MATCH(D45,$C$6:$C$35,0)) -> Emma Davis | D45: =LARGE($C$6:$C$35,A45) -> 8490.18 | E45: =INDEX($D$6:$D$35,MATCH(D45,$C$6:$C$35,0)) -> 2652.75
A46: 8 | B46: =INDEX($A$6:$A$35,MATCH(D46,$C$6:$C$35,0)) -> CUST012 | C46: =INDEX($B$6:$B$35,MATCH(D46,$C$6:$C$35,0)) -> Robert Anderson | D46: =LARGE($C$6:$C$35,A46) -> 8339 | E46: =INDEX($D$6:$D$35,MATCH(D46,$C$6:$C$35,0)) -> 2988.71
A47: 9 | B47: =INDEX($A$6:$A$35,MATCH(D47,$C$6:$C$35,0)) -> CUST030 | C47: =INDEX($B$6:$B$35,MATCH(D47,$C$6:$C$35,0)) -> James Wilson | D47: =LARGE($C$6:$C$35,A47) -> 7928.71 | E47: =INDEX($D$6:$D$35,MATCH(D47,$C$6:$C$35,0)) -> 2965.48
A48: 10 | B48: =INDEX($A$6:$A$35,MATCH(D48,$C$6:$C$35,0)) -> CUST004 | C48: =INDEX($B$6:$B$35,MATCH(D48,$C$6:$C$35,0)) -> Lisa Thomas | D48: =LARGE($C$6:$C$35,A48) -> 7813.59 | E48: =INDEX($D$6:$D$35,MATCH(D48,$C$6:$C$35,0)) -> 3211.82

Sheet Monthly Trend
A1: Monthly Sales Trend & Growth (with Up/Down Arrow formatting) | I1: Last month (helper): | J1: =EOMONTH(MAX(Dataset!$H$2:$H$201),-1)+1 -> 45748
A3: Month_Start | B3: Month | C3: Total_Sales | D3: Total_Profit | E3: Order_Count | F3: MoM_Sales_Growth
A4: =EOMONTH(MIN(Dataset!$H$2:$H$201),-1)+1 -> 45383 | B4: =IF(A4="","",TEXT(A4,"MMM-YYYY")) -> Apr-2024 | C4: =IF(A4="","",SUMIFS(Dataset!$E$2:$E$201,Dataset!$H$2:$H$201,">="&A4,Dataset!$H$2:$H$201,"<"&EDATE(A4,1))) -> 19029.96 | D4: =IF(A4="","",SUMIFS(Dataset!$I$2:$I$201,Dataset!$H$2:$H$201,">="&A4,Dataset!$H$2:$H$201,"<"&EDATE(A4,1))) -> 6244.01 | E4: =IF(A4="","",COUNTIFS(Dataset!$H$2:$H$201,">="&A4,Dataset!$H$2:$H$201,"<"&EDATE(A4,1))) -> 19 | F4: =""
A5: =IF(A4="","",IF(A4>=$J$1,"",EDATE(A4,1))) -> 45413 | B5: =IF(A5="","",TEXT(A5,"MMM-YYYY")) -> May-2024 | C5: =IF(A5="","",SUMIFS(Dataset!$E$2:$E$201,Dataset!$H$2:$H$201,">="&A5,Dataset!$H$2:$H$201,"<"&EDATE(A5,1))) -> 18507.34 | D5: =IF(A5="","",SUMIFS(Dataset!$I$2:$I$201,Dataset!$H$2:$H$201,">="&A5,Dataset!$H$2:$H$201,"<"&EDATE(A5,1))) -> 6121.35 | E5: =IF(A5="","",COUNTIFS(Dataset!$H$2:$H$201,">="&A5,Dataset!$H$2:$H$201,"<"&EDATE(A5,1))) -> 21 | F5: =IF(OR(A5="",C4=0,C4=""),"",(C5-C4)/C4) -> -0.027463011
A6: =IF(A5="","",IF(A5>=$J$1,"",EDATE(A5,1))) -> 45444 | B6: =IF(A6="","",TEXT(A6,"MMM-YYYY")) -> Jun-2024 | C6: =IF(A6="","",SUMIFS(Dataset!$E$2:$E$201,Dataset!$H$2:$H$201,">="&A6,Dataset!$H$2:$H$201,"<"&EDATE(A6,1))) -> 20187.51 | D6: =IF(A6="","",SUMIFS(Dataset!$I$2:$I$201,Dataset!$H$2:$H$201,">="&A6,Dataset!$H$2:$H$201,"<"&EDATE(A6,1))) -> 6918 | E6: =IF(A6="","",COUNTIFS(Dataset!$H$2:$H$201,">="&A6,Dataset!$H$2:$H$201,"<"&EDATE(A6,1))) -> 20 | F6: =IF(OR(A6="",C5=0,C5=""),"",(C6-C5)/C5) -> 0.090783981
A7: =IF(A6="","",IF(A6>=$J$1,"",EDATE(A6,1))) -> 45474 | B7: =IF(A7="","",TEXT(A7,"MMM-YYYY")) -> Jul-2024 | C7: =IF(A7="","",SUMIFS(Dataset!$E$2:$E$201,Dataset!$H$2:$H$201,">="&A7,Dataset!$H$2:$H$201,"<"&EDATE(A7,1))) -> 11609.04 | D7: =IF(A7="","",SUMIFS(Dataset!$I$2:$I$201,Dataset!$H$2:$H$201,">="&A7,Dataset!$H$2:$H$201,"<"&EDATE(A7,1))) -> 3743.85 | E7: =IF(A7="","",COUNTIFS(Dataset!$H$2:$H$201,">="&A7,Dataset!$H$2:$H$201,"<"&EDATE(A7,1))) -> 12 | F7: =IF(OR(A7="",C6=0,C6=""),"",(C7-C6)/C6) -> -0.42493948
A8: =IF(A7="","",IF(A7>=$J$1,"",EDATE(A7,1))) -> 45505 | B8: =IF(A8="","",TEXT(A8,"MMM-YYYY")) -> Aug-2024 | C8: =IF(A8="","",SUMIFS(Dataset!$E$2:$E$201,Dataset!$H$2:$H$201,">="&A8,Dataset!$H$2:$H$201,"<"&EDATE(A8,1))) -> 10091.7 | D8: =IF(A8="","",SUMIFS(Dataset!$I$2:$I$201,Dataset!$H$2:$H$201,">="&A8,Dataset!$H$2:$H$201,"<"&EDATE(A8,1))) -> 3302.84 | E8: =IF(A8="","",COUNTIFS(Dataset!$H$2:$H$201,">="&A8,Dataset!$H$2:$H$201,"<"&EDATE(A8,1))) -> 10 | F8: =IF(OR(A8="",C7=0,C7=""),"",(C8-C7)/C7) -> -0.13070331
A9: =IF(A8="","",IF(A8>=$J$1,"",EDATE(A8,1))) -> 45536 | B9: =IF(A9="","",TEXT(A9,"MMM-YYYY")) -> Sep-2024 | C9: =IF(A9="","",SUMIFS(Dataset!$E$2:$E$201,Dataset!$H$2:$H$201,">="&A9,Dataset!$H$2:$H$201,"<"&EDATE(A9,1))) -> 20533.5 | D9: =IF(A9="","",SUMIFS(Dataset!$I$2:$I$201,Dataset!$H$2:$H$201,">="&A9,Dataset!$H$2:$H$201,"<"&EDATE(A9,1))) -> 7457.52 | E9: =IF(A9="","",COUNTIFS(Dataset!$H$2:$H$201,">="&A9,Dataset!$H$2:$H$201,"<"&EDATE(A9,1))) -> 20 | F9: =IF(OR(A9="",C8=0,C8=""),"",(C9-C8)/C8) -> 1.0346919
A10: =IF(A9="","",IF(A9>=$J$1,"",EDATE(A9,1))) -> 45566 | B10: =IF(A10="","",TEXT(A10,"MMM-YYYY")) -> Oct-2024 | C10: =IF(A10="","",SUMIFS(Dataset!$E$2:$E$201,Dataset!$H$2:$H$201,">="&A10,Dataset!$H$2:$H$201,"<"&EDATE(A10,1))) -> 14215.24 | D10: =IF(A10="","",SUMIFS(Dataset!$I$2:$I$201,Dataset!$H$2:$H$201,">="&A10,Dataset!$H$2:$H$201,"<"&EDATE(A10,1))) -> 4861.7 | E10: =IF(A10="","",COUNTIFS(Dataset!$H$2:$H$201,">="&A10,Dataset!$H$2:$H$201,"<"&EDATE(A10,1))) -> 14 | F10: =IF(OR(A10="",C9=0,C9=""),"",(C10-C9)/C9) -> -0.30770497
A11: =IF(A10="","",IF(A10>=$J$1,"",EDATE(A10,1))) -> 45597 | B11: =IF(A11="","",TEXT(A11,"MMM-YYYY")) -> Nov-2024 | C11: =IF(A11="","",SUMIFS(Dataset!$E$2:$E$201,Dataset!$H$2:$H$201,">="&A11,Dataset!$H$2:$H$201,"<"&EDATE(A11,1))) -> 20135.03 | D11: =IF(A11="","",SUMIFS(Dataset!$I$2:$I$201,Dataset!$H$2:$H$201,">="&A11,Dataset!$H$2:$H$201,"<"&EDATE(A11,1))) -> 6814.88 | E11: =IF(A11="","",COUNTIFS(Dataset!$H$2:$H$201,">="&A11,Dataset!$H$2:$H$201,"<"&EDATE(A11,1))) -> 20 | F11: =IF(OR(A11="",C10=0,C10=""),"",(C11-C10)/C10) -> 0.41643968
A12: =IF(A11="","",IF(A11>=$J$1,"",EDATE(A11,1))) -> 45627 | B12: =IF(A12="","",TEXT(A12,"MMM-YYYY")) -> Dec-2024 | C12: =IF(A12="","",SUMIFS(Dataset!$E$2:$E$201,Dataset!$H$2:$H$201,">="&A12,Dataset!$H$2:$H$201,"<"&EDATE(A12,1))) -> 11120.04 | D12: =IF(A12="","",SUMIFS(Dataset!$I$2:$I$201,Dataset!$H$2:$H$201,">="&A12,Dataset!$H$2:$H$201,"<"&EDATE(A12,1))) -> 3549.99 | E12: =IF(A12="","",COUNTIFS(Dataset!$H$2:$H$201,">="&A12,Dataset!$H$2:$H$201,"<"&EDATE(A12,1))) -> 11 | F12: =IF(OR(A12="",C11=0,C11=""),"",(C12-C11)/C11) -> -0.44772667
A13: =IF(A12="","",IF(A12>=$J$1,"",EDATE(A12,1))) -> 45658 | B13: =IF(A13="","",TEXT(A13,"MMM-YYYY")) -> Jan-2025 | C13: =IF(A13="","",SUMIFS(Dataset!$E$2:$E$201,Dataset!$H$2:$H$201,">="&A13,Dataset!$H$2:$H$201,"<"&EDATE(A13,1))) -> 14914.65 | D13: =IF(A13="","",SUMIFS(Dataset!$I$2:$I$201,Dataset!$H$2:$H$201,">="&A13,Dataset!$H$2:$H$201,"<"&EDATE(A13,1))) -> 5763.4 | E13: =IF(A13="","",COUNTIFS(Dataset!$H$2:$H$201,">="&A13,Dataset!$H$2:$H$201,"<"&EDATE(A13,1))) -> 16 | F13: =IF(OR(A13="",C12=0,C12=""),"",(C13-C12)/C12) -> 0.34124068
A14: =IF(A13="","",IF(A13>=$J$1,"",EDATE(A13,1))) -> 45689 | B14: =IF(A14="","",TEXT(A14,"MMM-YYYY")) -> Feb-2025 | C14: =IF(A14="","",SUMIFS(Dataset!$E$2:$E$201,Dataset!$H$2:$H$201,">="&A14,Dataset!$H$2:$H$201,"<"&EDATE(A14,1))) -> 14006.36 | D14: =IF(A14="","",SUMIFS(Dataset!$I$2:$I$201,Dataset!$H$2:$H$201,">="&A14,Dataset!$H$2:$H$201,"<"&EDATE(A14,1))) -> 5039.23 | E14: =IF(A14="","",COUNTIFS(Dataset!$H$2:$H$201,">="&A14,Dataset!$H$2:$H$201,"<"&EDATE(A14,1))) -> 14 | F14: =IF(OR(A14="",C13=0,C13=""),"",(C14-C13)/C13) -> -0.060899183
A15: =IF(A14="","",IF(A14>=$J$1,"",EDATE(A14,1))) -> 45717 | B15: =IF(A15="","",TEXT(A15,"MMM-YYYY")) -> Mar-2025 | C15: =IF(A15="","",SUMIFS(Dataset!$E$2:$E$201,Dataset!$H$2:$H$201,">="&A15,Dataset!$H$2:$H$201,"<"&EDATE(A15,1))) -> 17655.22 | D15: =IF(A15="","",SUMIFS(Dataset!$I$2:$I$201,Dataset!$H$2:$H$201,">="&A15,Dataset!$H$2:$H$201,"<"&EDATE(A15,1))) -> 7071.39 | E15: =IF(A15="","",COUNTIFS(Dataset!$H$2:$H$201,">="&A15,Dataset!$H$2:$H$201,"<"&EDATE(A15,1))) -> 19 | F15: =IF(OR(A15="",C14=0,C14=""),"",(C15-C14)/C14) -> 0.26051451
A16: =IF(A15="","",IF(A15>=$J$1,"",EDATE(A15,1))) -> 45748 | B16: =IF(A16="","",TEXT(A16,"MMM-YYYY")) -> Apr-2025 | C16: =IF(A16="","",SUMIFS(Dataset!$E$2:$E$201,Dataset!$H$2:$H$201,">="&A16,Dataset!$H$2:$H$201,"<"&EDATE(A16,1))) -> 3212.17 | D16: =IF(A16="","",SUMIFS(Dataset!$I$2:$I$201,Dataset!$H$2:$H$201,">="&A16,Dataset!$H$2:$H$201,"<"&EDATE(A16,1))) -> 1398.85 | E16: =IF(A16="","",COUNTIFS(Dataset!$H$2:$H$201,">="&A16,Dataset!$H$2:$H$201,"<"&EDATE(A16,1))) -> 4 | F16: =IF(OR(A16="",C15=0,C15=""),"",(C16-C15)/C15) -> -0.81806117
... A18: =IF(A17="","",IF(A17>=$J$1,"",EDATE(A17,1))) | B18: =IF(A18="","",TEXT(A18,"MMM-YYYY")) | C18: =IF(A18="","",SUMIFS(Dataset!$E$2:$E$201,Dataset!$H$2:$H$201,">="&A18,Dataset!$H$2:$H$201,"<"&EDATE(A18,1))) | D18: =IF(A18="","",SUMIFS(Dataset!$I$2:$I$201,Dataset!$H$2:$H$201,">="&A18,Dataset!$H$2:$H$201,"<"&EDATE(A18,1))) | E18: =IF(A18="","",COUNTIFS(Dataset!$H$2:$H$201,">="&A18,Dataset!$H$2:$H$201,"<"&EDATE(A18,1))) | F18: =IF(OR(A18="",C17=0,C17=""),"",(C18-C17)/C17)

Sheet What-If Analysis
A1: What-If Analysis: Impact of Discount Changes on Total Profit
B3: Current Average Discount | C3: =AVERAGE(Dataset!$G$2:$G$201) -> 0.09725
B4: Current Total Sales | C4: =SUM(Dataset!$E$2:$E$201) -> 195217.76
B5: Current Total Profit | C5: =SUM(Dataset!$I$2:$I$201) -> 68287.01
B7: Adjust Discount Rate (Input) | C7: 0.1
B8: Projected Total Profit at New Discount | C8: =SUMPRODUCT(Dataset!$I$2:$I$201*(1-$C$7)/(1-Dataset!$G$2:$G$201)) -> 68151.771
B9: Profit Change ($) | C9: =C8-C5 -> -135.23913
B10: Profit Change (%) | C10: =IFERROR(C9/C5,"") -> -0.0019804518
B13: Discount Scenario Sensitivity Table
B14: Discount_Scenario | C14: Total_Profit | D14: Change_vs_Current ($) | E14: Change_vs_Current (%)
B15: 0 | C15: =SUMPRODUCT(Dataset!$I$2:$I$201*(1-B15)/(1-Dataset!$G$2:$G$201)) -> 75724.19 | D15: =C15-$C$5 -> 7437.1799 | E15: =IFERROR(D15/$C$5,"") -> 0.10891061
B16: 0.05 | C16: =SUMPRODUCT(Dataset!$I$2:$I$201*(1-B16)/(1-Dataset!$G$2:$G$201)) -> 71937.98 | D16: =C16-$C$5 -> 3650.9704 | E16: =IFERROR(D16/$C$5,"") -> 0.053465079
B17: 0.1 | C17: =SUMPRODUCT(Dataset!$I$2:$I$201*(1-B17)/(1-Dataset!$G$2:$G$201)) -> 68151.771 | D17: =C17-$C$5 -> -135.23913 | E17: =IFERROR(D17/$C$5,"") -> -0.0019804518
B18: 0.15 | C18: =SUMPRODUCT(Dataset!$I$2:$I$201*(1-B18)/(1-Dataset!$G$2:$G$201)) -> 64365.561 | D18: =C18-$C$5 -> -3921.4486 | E18: =IFERROR(D18/$C$5,"") -> -0.057425982
B19: 0.2 | C19: =SUMPRODUCT(Dataset!$I$2:$I$201*(1-B19)/(1-Dataset!$G$2:$G$201)) -> 60579.352 | D19: =C19-$C$5 -> -7707.6581 | E19: =IFERROR(D19/$C$5,"") -> -0.11287151
B20: 0.25 | C20: =SUMPRODUCT(Dataset!$I$2:$I$201*(1-B20)/(1-Dataset!$G$2:$G$201)) -> 56793.142 | D20: =C20-$C$5 -> -11493.868 | E20: =IFERROR(D20/$C$5,"") -> -0.16831704
B21: 0.3 | C21: =SUMPRODUCT(Dataset!$I$2:$I$201*(1-B21)/(1-Dataset!$G$2:$G$201)) -> 53006.933 | D21: =C21-$C$5 -> -15280.077 | E21: =IFERROR(D21/$C$5,"") -> -0.22376257
B22: 0.35 | C22: =SUMPRODUCT(Dataset!$I$2:$I$201*(1-B22)/(1-Dataset!$G$2:$G$201)) -> 49220.723 | D22: =C22-$C$5 -> -19066.287 | E22: =IFERROR(D22/$C$5,"") -> -0.2792081

Sheet Regression Analysis
A1: Linear Regression: Profit vs Sales (Data Analysis Toolpak equivalent)
B3: Regression Statistics
B4: Multiple R | C4: =CORREL(Dataset!$I$2:$I$201,Dataset!$E$2:$E$201) -> 0.77340306
B5: R Square | C5: =RSQ(Dataset!$I$2:$I$201,Dataset!$E$2:$E$201) -> 0.5981523
B6: Adjusted R Square | C6: =1-((1-C4)*(C7-1)/(C7-2)) -> 0.77071448
B7: Standard Error | C7: =STEYX(Dataset!$I$2:$I$201,Dataset!$E$2:$E$201) -> 86.281231
B8: Observations | C8: =COUNT(Dataset!$E$2:$E$201) -> 200
B10: Coefficients Table
C11: Coefficients | D11: Standard Error | E11: t Stat | F11: P-value
B12: Intercept | C12: =INTERCEPT(Dataset!$I$2:$I$201,Dataset!$E$2:$E$201) -> -1.0315505 | D12: =$C$6*SQRT(1/$C$7+AVERAGE(Dataset!$E$2:$E$201)^2/DEVSQ(Dataset!$E$2:$E$201)) -> 0.19656242 | E12: =C12/D12 -> -5.2479538 | F12: =TDIST(ABS(E12),$C$7-2,2) -> 1.1362068e-06
B13: Sales (X Variable) | C13: =SLOPE(Dataset!$I$2:$I$201,Dataset!$E$2:$E$201) -> 0.35085599 | D13: =$C$6/SQRT(DEVSQ(Dataset!$E$2:$E$201)) -> 0.00018255694 | E13: =C13/D13 -> 1921.899 | F13: =TDIST(ABS(E13),$C$7-2,2) -> 8.4035296e-197
B16: Regression Equation | C16: ="Profit = "&TEXT(C13,"0.0000")&" x Sales + "&TEXT(C12,"0.0000") -> Profit = 0.3509 x Sales + -1.0316
B18: Insight (auto-generated) | C18: ="For every $1 increase in Sales, Profit increases by approximately $"&TEXT(C13,"0.00")&" on average. The model explains "&TEXT(C4,"0.0%")&" of the variation in Profit (R Square)." -> For every $1 increase in Sales, Profit increases by approximately $0.35 on average. The model explains 77.3% of the variation in Profit (R Square).

Sheet Descriptive Statistics
A1: Descriptive Statistics (Data Analysis Toolpak equivalent)
A3: Statistic | B3: Sales | C3: Quantity | D3: Discount | E3: Profit
A4: Mean | B4: =AVERAGE(Dataset!$E$2:$E$201) -> 976.0888 | C4: =AVERAGE(Dataset!$F$2:$F$201) -> 9.995 | D4: =AVERAGE(Dataset!$G$2:$G$201) -> 0.09725 | E4: =AVERAGE(Dataset!$I$2:$I$201) -> 341.43505
A5: Standard Error | B5: =STDEV(Dataset!$E$2:$E$201)/SQRT(COUNT(Dataset!$E$2:$E$201)) -> 21.16185 | C5: =STDEV(Dataset!$F$2:$F$201)/SQRT(COUNT(Dataset!$F$2:$F$201)) -> 0.39927683 | D5: =STDEV(Dataset!$G$2:$G$201)/SQRT(COUNT(Dataset!$G$2:$G$201)) -> 0.0051142414 | E5: =STDEV(Dataset!$I$2:$I$201)/SQRT(COUNT(Dataset!$I$2:$I$201)) -> 9.6001196
A6: Median | B6: =MEDIAN(Dataset!$E$2:$E$201) -> 976.72 | C6: =MEDIAN(Dataset!$F$2:$F$201) -> 10 | D6: =MEDIAN(Dataset!$G$2:$G$201) -> 0.1 | E6: =MEDIAN(Dataset!$I$2:$I$201) -> 332.255
A7: Mode | B7: =IFERROR(MODE(Dataset!$E$2:$E$201),"N/A") -> N/A | C7: =IFERROR(MODE(Dataset!$F$2:$F$201),"N/A") -> 8 | D7: =IFERROR(MODE(Dataset!$G$2:$G$201),"N/A") -> 0.2 | E7: =IFERROR(MODE(Dataset!$I$2:$I$201),"N/A") -> N/A
A8: Standard Deviation | B8: =STDEV(Dataset!$E$2:$E$201) -> 299.27376 | C8: =STDEV(Dataset!$F$2:$F$201) -> 5.646627 | D8: =STDEV(Dataset!$G$2:$G$201) -> 0.072326295 | E8: =STDEV(Dataset!$I$2:$I$201) -> 135.76619
A9: Sample Variance | B9: =VAR(Dataset!$E$2:$E$201) -> 89564.783 | C9: =VAR(Dataset!$F$2:$F$201) -> 31.884397 | D9: =VAR(Dataset!$G$2:$G$201) -> 0.005231093 | E9: =VAR(Dataset!$I$2:$I$201) -> 18432.459
A10: Kurtosis | B10: =KURT(Dataset!$E$2:$E$201) -> -0.088595232 | C10: =KURT(Dataset!$F$2:$F$201) -> -1.2091054 | D10: =KURT(Dataset!$G$2:$G$201) -> -1.3257012 | E10: =KURT(Dataset!$I$2:$I$201) -> 0.26450644
A11: Skewness | B11: =SKEW(Dataset!$E$2:$E$201) -> 0.14685797 | C11: =SKEW(Dataset!$F$2:$F$201) -> 0.060845864 | D11: =SKEW(Dataset!$G$2:$G$201) -> 0.096827386 | E11: =SKEW(Dataset!$I$2:$I$201) -> 0.57339636
A12: Range | B12: =MAX(Dataset!$E$2:$E$201)-MIN(Dataset!$E$2:$E$201) -> 1665.15 | C12: =MAX(Dataset!$F$2:$F$201)-MIN(Dataset!$F$2:$F$201) -> 18 | D12: =MAX(Dataset!$G$2:$G$201)-MIN(Dataset!$G$2:$G$201) -> 0.2 | E12: =MAX(Dataset!$I$2:$I$201)-MIN(Dataset!$I$2:$I$201) -> 704.83
A13: Minimum | B13: =MIN(Dataset!$E$2:$E$201) -> 258.51 | C13: =MIN(Dataset!$F$2:$F$201) -> 1 | D13: =MIN(Dataset!$G$2:$G$201) -> 0 | E13: =MIN(Dataset!$I$2:$I$201) -> 64.63
A14: Maximum | B14: =MAX(Dataset!$E$2:$E$201) -> 1923.66 | C14: =MAX(Dataset!$F$2:$F$201) -> 19 | D14: =MAX(Dataset!$G$2:$G$201) -> 0.2 | E14: =MAX(Dataset!$I$2:$I$201) -> 769.46
A15: Sum | B15: =SUM(Dataset!$E$2:$E$201) -> 195217.76 | C15: =SUM(Dataset!$F$2:$F$201) -> 1999 | D15: =SUM(Dataset!$G$2:$G$201) -> 19.45 | E15: =SUM(Dataset!$I$2:$I$201) -> 68287.01
A16: Count | B16: =COUNT(Dataset!$E$2:$E$201) -> 200 | C16: =COUNT(Dataset!$F$2:$F$201) -> 200 | D16: =COUNT(Dataset!$G$2:$G$201) -> 200 | E16: =COUNT(Dataset!$I$2:$I$201) -> 200

Sheet Pivot Summary
A1: Pivot Table Summary: Sales & Profit by Region and Category
A3: Built with SUMIFS so it recalculates live from the Dataset sheet (safer across Excel/LibreOffice than a native embedded PivotTable). To get an interactive drag-and-drop PivotTable as well, select Dataset!A1:I201 and use Insert > PivotTable.
A5: Total Sales by Region x Product Category
A6: Region | B6: Books | C6: Clothing | D6: Electronics | E6: Furniture | F6: Office Supplies | G6: Grand Total
A7: West | B7: =SUMIFS(Dataset!$E$2:$E$201,Dataset!$C$2:$C$201,$A7,Dataset!$D$2:$D$201,B$6) -> 6691.17 | C7: =SUMIFS(Dataset!$E$2:$E$201,Dataset!$C$2:$C$201,$A7,Dataset!$D$2:$D$201,C$6) -> 10509.43 | D7: =SUMIFS(Dataset!$E$2:$E$201,Dataset!$C$2:$C$201,$A7,Dataset!$D$2:$D$201,D$6) -> 11372.44 | E7: =SUMIFS(Dataset!$E$2:$E$201,Dataset!$C$2:$C$201,$A7,Dataset!$D$2:$D$201,E$6) -> 9182.78 | F7: =SUMIFS(Dataset!$E$2:$E$201,Dataset!$C$2:$C$201,$A7,Dataset!$D$2:$D$201,F$6) -> 6327.76 | G7: =SUM(B7:F7) -> 44083.58
A8: East | B8: =SUMIFS(Dataset!$E$2:$E$201,Dataset!$C$2:$C$201,$A8,Dataset!$D$2:$D$201,B$6) -> 11389.09 | C8: =SUMIFS(Dataset!$E$2:$E$201,Dataset!$C$2:$C$201,$A8,Dataset!$D$2:$D$201,C$6) -> 2401.45 | D8: =SUMIFS(Dataset!$E$2:$E$201,Dataset!$C$2:$C$201,$A8,Dataset!$D$2:$D$201,D$6) -> 2869.54 | E8: =SUMIFS(Dataset!$E$2:$E$201,Dataset!$C$2:$C$201,$A8,Dataset!$D$2:$D$201,E$6) -> 7592.34 | F8: =SUMIFS(Dataset!$E$2:$E$201,Dataset!$C$2:$C$201,$A8,Dataset!$D$2:$D$201,F$6) -> 8189.22 | G8: =SUM(B8:F8) -> 32441.64
A9: South | B9: =SUMIFS(Dataset!$E$2:$E$201,Dataset!$C$2:$C$201,$A9,Dataset!$D$2:$D$201,B$6) -> 9588.04 | C9: =SUMIFS(Dataset!$E$2:$E$201,Dataset!$C$2:$C$201,$A9,Dataset!$D$2:$D$201,C$6) -> 8393.63 | D9: =SUMIFS(Dataset!$E$2:$E$201,Dataset!$C$2:$C$201,$A9,Dataset!$D$2:$D$201,D$6) -> 11989.07 | E9: =SUMIFS(Dataset!$E$2:$E$201,Dataset!$C$2:$C$201,$A9,Dataset!$D$2:$D$201,E$6) -> 7982.73 | F9: =SUMIFS(Dataset!$E$2:$E$201,Dataset!$C$2:$C$201,$A9,Dataset!$D$2:$D$201,F$6) -> 2295.32 | G9: =SUM(B9:F9) -> 40248.79
A10: North | B10: =SUMIFS(Dataset!$E$2:$E$201,Dataset!$C$2:$C$201,$A10,Dataset!$D$2:$D$201,B$6) -> 8037.01 | C10: =SUMIFS(Dataset!$E$2:$E$201,Dataset!$C$2:$C$201,$A10,Dataset!$D$2:$D$201,C$6) -> 8422.82 | D10: =SUMIFS(Dataset!$E$2:$E$201,Dataset!$C$2:$C$201,$A10,Dataset!$D$2:$D$201,D$6) -> 8191.71 | E10: =SUMIFS(Dataset!$E$2:$E$201,Dataset!$C$2:$C$201,$A10,Dataset!$D$2:$D$201,E$6) -> 6978.08 | F10: =SUMIFS(Dataset!$E$2:$E$201,Dataset!$C$2:$C$201,$A10,Dataset!$D$2:$D$201,F$6) -> 3345.8 | G10: =SUM(B10:F10) -> 34975.42
A11: Central | B11: =SUMIFS(Dataset!$E$2:$E$201,Dataset!$C$2:$C$201,$A11,Dataset!$D$2:$D$201,B$6) -> 11297.15 | C11: =SUMIFS(Dataset!$E$2:$E$201,Dataset!$C$2:$C$201,$A11,Dataset!$D$2:$D$201,C$6) -> 12200.26 | D11: =SUMIFS(Dataset!$E$2:$E$201,Dataset!$C$2:$C$201,$A11,Dataset!$D$2:$D$201,D$6) -> 6621.24 | E11: =SUMIFS(Dataset!$E$2:$E$201,Dataset!$C$2:$C$201,$A11,Dataset!$D$2:$D$201,E$6) -> 4876.96 | F11: =SUMIFS(Dataset!$E$2:$E$201,Dataset!$C$2:$C$201,$A11,Dataset!$D$2:$D$201,F$6) -> 8472.72 | G11: =SUM(B11:F11) -> 43468.33
A12: Grand Total | B12: =SUM(B7:B11) -> 47002.46 | C12: =SUM(C7:C11) -> 41927.59 | D12: =SUM(D7:D11) -> 41044 | E12: =SUM(E7:E11) -> 36612.89 | F12: =SUM(F7:F11) -> 28630.82 | G12: =SUM(G7:G11) -> 195217.76
A15: Total Profit by Region x Product Category
A16: Region | B16: Books | C16: Clothing | D16: Electronics | E16: Furniture | F16: Office Supplies | G16: Grand Total
A17: West | B17: =SUMIFS(Dataset!$I$2:$I$201,Dataset!$C$2:$C$201,$A17,Dataset!$D$2:$D$201,B$16) -> 2292.48 | C17: =SUMIFS(Dataset!$I$2:$I$201,Dataset!$C$2:$C$201,$A17,Dataset!$D$2:$D$201,C$16) -> 4728.44 | D17: =SUMIFS(Dataset!$I$2:$I$201,Dataset!$C$2:$C$201,$A17,Dataset!$D$2:$D$201,D$16) -> 2437.94 | E17: =SUMIFS(Dataset!$I$2:$I$201,Dataset!$C$2:$C$201,$A17,Dataset!$D$2:$D$201,E$16) -> 2826.52 | F17: =SUMIFS(Dataset!$I$2:$I$201,Dataset!$C$2:$C$201,$A17,Dataset!$D$2:$D$201,F$16) -> 2700.45 | G17: =SUM(B17:F17) -> 14985.83
A18: East | B18: =SUMIFS(Dataset!$I$2:$I$201,Dataset!$C$2:$C$201,$A18,Dataset!$D$2:$D$201,B$16) -> 4212.63 | C18: =SUMIFS(Dataset!$I$2:$I$201,Dataset!$C$2:$C$201,$A18,Dataset!$D$2:$D$201,C$16) -> 1025.15 | D18: =SUMIFS(Dataset!$I$2:$I$201,Dataset!$C$2:$C$201,$A18,Dataset!$D$2:$D$201,D$16) -> 662.68 | E18: =SUMIFS(Dataset!$I$2:$I$201,Dataset!$C$2:$C$201,$A18,Dataset!$D$2:$D$201,E$16) -> 2428.08 | F18: =SUMIFS(Dataset!$I$2:$I$201,Dataset!$C$2:$C$201,$A18,Dataset!$D$2:$D$201,F$16) -> 3310.05 | G18: =SUM(B18:F18) -> 11638.59
A19: South | B19: =SUMIFS(Dataset!$I$2:$I$201,Dataset!$C$2:$C$201,$A19,Dataset!$D$2:$D$201,B$16) -> 3416.81 | C19: =SUMIFS(Dataset!$I$2:$I$201,Dataset!$C$2:$C$201,$A19,Dataset!$D$2:$D$201,C$16) -> 3944.21 | D19: =SUMIFS(Dataset!$I$2:$I$201,Dataset!$C$2:$C$201,$A19,Dataset!$D$2:$D$201,D$16) -> 2783.44 | E19: =SUMIFS(Dataset!$I$2:$I$201,Dataset!$C$2:$C$201,$A19,Dataset!$D$2:$D$201,E$16) -> 2540.36 | F19: =SUMIFS(Dataset!$I$2:$I$201,Dataset!$C$2:$C$201,$A19,Dataset!$D$2:$D$201,F$16) -> 1007.09 | G19: =SUM(B19:F19) -> 13691.91
A20: North | B20: =SUMIFS(Dataset!$I$2:$I$201,Dataset!$C$2:$C$201,$A20,Dataset!$D$2:$D$201,B$16) -> 2778.44 | C20: =SUMIFS(Dataset!$I$2:$I$201,Dataset!$C$2:$C$201,$A20,Dataset!$D$2:$D$201,C$16) -> 3691.09 | D20: =SUMIFS(Dataset!$I$2:$I$201,Dataset!$C$2:$C$201,$A20,Dataset!$D$2:$D$201,D$16) -> 1783.05 | E20: =SUMIFS(Dataset!$I$2:$I$201,Dataset!$C$2:$C$201,$A20,Dataset!$D$2:$D$201,E$16) -> 2217.72 | F20: =SUMIFS(Dataset!$I$2:$I$201,Dataset!$C$2:$C$201,$A20,Dataset!$D$2:$D$201,F$16) -> 1431.98 | G20: =SUM(B20:F20) -> 11902.28
A21: Central | B21: =SUMIFS(Dataset!$I$2:$I$201,Dataset!$C$2:$C$201,$A21,Dataset!$D$2:$D$201,B$16) -> 4201.27 | C21: =SUMIFS(Dataset!$I$2:$I$201,Dataset!$C$2:$C$201,$A21,Dataset!$D$2:$D$201,C$16) -> 5395.6 | D21: =SUMIFS(Dataset!$I$2:$I$201,Dataset!$C$2:$C$201,$A21,Dataset!$D$2:$D$201,D$16) -> 1515.04 | E21: =SUMIFS(Dataset!$I$2:$I$201,Dataset!$C$2:$C$201,$A21,Dataset!$D$2:$D$201,E$16) -> 1566.46 | F21: =SUMIFS(Dataset!$I$2:$I$201,Dataset!$C$2:$C$201,$A21,Dataset!$D$2:$D$201,F$16) -> 3390.03 | G21: =SUM(B21:F21) -> 16068.4
A22: Grand Total | B22: =SUM(B17:B21) -> 16901.63 | C22: =SUM(C17:C21) -> 18784.49 | D22: =SUM(D17:D21) -> 9182.15 | E22: =SUM(E17:E21) -> 11579.14 | F22: =SUM(F17:F21) -> 11839.6 | G22: =SUM(G17:G21) -> 68287.01
